MANIFEST.in
README.rst
setup.cfg
setup.py
kombu_stomp/__init__.py
kombu_stomp/jms.py
kombu_stomp/stomp.py
kombu_stomp/transport.py
kombu_stomp/utils.py
kombu_stomp.egg-info/PKG-INFO
kombu_stomp.egg-info/SOURCES.txt
kombu_stomp.egg-info/dependency_links.txt
kombu_stomp.egg-info/requires.txt
kombu_stomp.egg-info/top_level.txt
kombu_stomp.egg-info/zip-safe
requirements/base.txt
requirements/dev.txt
requirements/tests.txt